mcp_youtube_transcript/__init__.py
mcp_youtube_transcript/__main__.py
mcp_youtube_transcript/cli.py
iflow_mcp_mcp_youtube_transcript-0.5.6.dist-info/METADATA
iflow_mcp_mcp_youtube_transcript-0.5.6.dist-info/WHEEL
iflow_mcp_mcp_youtube_transcript-0.5.6.dist-info/entry_points.txt
iflow_mcp_mcp_youtube_transcript-0.5.6.dist-info/licenses/LICENSE
iflow_mcp_mcp_youtube_transcript-0.5.6.dist-info/RECORD
